hellorwid/__init__.py
hellorwid/main.py
hellorwid-0.0.5.dist-info/LICENSE
hellorwid-0.0.5.dist-info/METADATA
hellorwid-0.0.5.dist-info/WHEEL
hellorwid-0.0.5.dist-info/top_level.txt
hellorwid-0.0.5.dist-info/RECORD
