Metadata-Version: 2.1
Name: hellorwid
Version: 0.0.5
Summary: A hello world for all fellows of Remote Worker Indonesia
Home-page: https://github.com/remoteworkerid/hellorwid
Author: Eko S. Wibowo
Author-email: swdev.bali@gmail.com
License: UNKNOWN
Platform: UNKNOWN
Classifier: Programming Language :: Python :: 3
Classifier: License :: OSI Approved :: GNU General Public License v3 (GPLv3)
Classifier: Operating System :: OS Independent
Classifier: Development Status :: 4 - Beta
Requires-Python: >=3.6
